tlslite/__init__.py
tlslite/api.py
tlslite/basedb.py
tlslite/bufferedsocket.py
tlslite/checker.py
tlslite/constants.py
tlslite/defragmenter.py
tlslite/dh.py
tlslite/errors.py
tlslite/extensions.py
tlslite/handshakehashes.py
tlslite/handshakehelpers.py
tlslite/handshakesettings.py
tlslite/keyexchange.py
tlslite/mathtls.py
tlslite/messages.py
tlslite/messagesocket.py
tlslite/ocsp.py
tlslite/recordlayer.py
tlslite/session.py
tlslite/sessioncache.py
tlslite/signed.py
tlslite/tlsconnection.py
tlslite/tlsrecordlayer.py
tlslite/verifierdb.py
tlslite/x509.py
tlslite/x509certchain.py
tlslite/integration/__init__.py
tlslite/integration/asyncstatemachine.py
tlslite/integration/clienthelper.py
tlslite/integration/httptlsconnection.py
tlslite/integration/imap4_tls.py
tlslite/integration/pop3_tls.py
tlslite/integration/smtp_tls.py
tlslite/integration/tlsasyncdispatchermixin.py
tlslite/integration/tlsasynciodispatchermixin.py
tlslite/integration/tlssocketservermixin.py
tlslite/integration/xmlrpcserver.py
tlslite/integration/xmlrpctransport.py
tlslite/utils/__init__.py
tlslite/utils/aes.py
tlslite/utils/aesccm.py
tlslite/utils/aesgcm.py
tlslite/utils/asn1parser.py
tlslite/utils/chacha.py
tlslite/utils/chacha20_poly1305.py
tlslite/utils/cipherfactory.py
tlslite/utils/codec.py
tlslite/utils/compat.py
tlslite/utils/compression.py
tlslite/utils/constanttime.py
tlslite/utils/cryptomath.py
tlslite/utils/datefuncs.py
tlslite/utils/deprecations.py
tlslite/utils/dns_utils.py
tlslite/utils/dsakey.py
tlslite/utils/ecc.py
tlslite/utils/ecdsakey.py
tlslite/utils/eddsakey.py
tlslite/utils/format_output.py
tlslite/utils/keyfactory.py
tlslite/utils/lists.py
tlslite/utils/openssl_aes.py
tlslite/utils/openssl_aesccm.py
tlslite/utils/openssl_aesgcm.py
tlslite/utils/openssl_rc4.py
tlslite/utils/openssl_rsakey.py
tlslite/utils/openssl_tripledes.py
tlslite/utils/pem.py
tlslite/utils/poly1305.py
tlslite/utils/pycrypto_aes.py
tlslite/utils/pycrypto_aesgcm.py
tlslite/utils/pycrypto_rc4.py
tlslite_ng-0.8.1.dist-info/LICENSE
tlslite_ng-0.8.1.dist-info/METADATA
tlslite_ng-0.8.1.dist-info/WHEEL
tlslite_ng-0.8.1.dist-info/top_level.txt
tlslite_ng-0.8.1.dist-info/RECORD
